fakenews/__init__.py
fakenews/apps.py
fakenews/models.py
fakenews/management/commands/make_fake_items.py
fakenews/migrations/0001_initial.py
fakenews/migrations/__init__.py
fakenews/templates/fakenews/fake_news_index_page.html
fakenews/templates/fakenews/fake_news_page.html
wagtail_fakenews-0.1.2.dist-info/LICENSE
wagtail_fakenews-0.1.2.dist-info/METADATA
wagtail_fakenews-0.1.2.dist-info/WHEEL
wagtail_fakenews-0.1.2.dist-info/pbr.json
wagtail_fakenews-0.1.2.dist-info/top_level.txt
wagtail_fakenews-0.1.2.dist-info/RECORD
