Metadata-Version: 2.1
Name: wagtail-fakenews
Version: 0.1.2
Summary: Create fake Wagtail pages
Home-page: https://github.com/tomdyson/wagtail-fakenews
Author: Tom Dyson
Author-email: tom+wagtailfakenews@torchbox.com
License: MIT
Keywords: development
Platform: UNKNOWN
Classifier: Environment :: Web Environment
Classifier: Framework :: Django
Classifier: Framework :: Wagtail
Classifier: Framework :: Wagtail :: 2
Classifier: Intended Audience :: Developers
Classifier: Operating System :: OS Independent
Classifier: Programming Language :: Python
Classifier: Topic :: Internet :: WWW/HTTP
Classifier: Topic :: Internet :: WWW/HTTP :: Dynamic Content
Requires-Dist: wagtail (>=2.8)
Requires-Dist: Faker (>=4.1.1)
